{
   "runs" : [
      {
         "OS" : "linux",
         "abstract" : "Enforce abstract (non-instantiable) base classes for plain-Perl OO",
         "dir" : "/home/runner/work/Class-Abstract/Class-Abstract",
         "finish" : 1781180990.40196,
         "name" : "Class-Abstract",
         "perl" : "5.40.4",
         "run" : "-e",
         "start" : 1781180986.02388,
         "version" : "0.01"
      },
      {
         "OS" : "linux",
         "abstract" : "Enforce abstract (non-instantiable) base classes for plain-Perl OO",
         "dir" : "/home/runner/work/Class-Abstract/Class-Abstract",
         "finish" : 1781180986.16608,
         "name" : "Class-Abstract",
         "perl" : "5.40.4",
         "run" : "-e",
         "start" : 1781180986.16599,
         "version" : "0.01"
      },
      {
         "OS" : "linux",
         "abstract" : "Enforce abstract (non-instantiable) base classes for plain-Perl OO",
         "dir" : "/home/runner/work/Class-Abstract/Class-Abstract",
         "finish" : 1781180986.45086,
         "name" : "Class-Abstract",
         "perl" : "5.40.4",
         "run" : "t/00-load.t",
         "start" : 1781180986.4257,
         "version" : "0.01"
      },
      {
         "OS" : "linux",
         "abstract" : "Enforce abstract (non-instantiable) base classes for plain-Perl OO",
         "dir" : "/home/runner/work/Class-Abstract/Class-Abstract",
         "finish" : 1781180986.7924,
         "name" : "Class-Abstract",
         "perl" : "5.40.4",
         "run" : "t/basic.t",
         "start" : 1781180986.77404,
         "version" : "0.01"
      },
      {
         "OS" : "linux",
         "abstract" : "Enforce abstract (non-instantiable) base classes for plain-Perl OO",
         "dir" : "/home/runner/work/Class-Abstract/Class-Abstract",
         "finish" : 1781180987.13392,
         "name" : "Class-Abstract",
         "perl" : "5.40.4",
         "run" : "t/bypass.t",
         "start" : 1781180987.11908,
         "version" : "0.01"
      },
      {
         "OS" : "linux",
         "abstract" : "Enforce abstract (non-instantiable) base classes for plain-Perl OO",
         "dir" : "/home/runner/work/Class-Abstract/Class-Abstract",
         "finish" : 1781180987.53731,
         "name" : "Class-Abstract",
         "perl" : "5.40.4",
         "run" : "t/edge_cases.t",
         "start" : 1781180987.46026,
         "version" : "0.01"
      },
      {
         "OS" : "linux",
         "abstract" : "Enforce abstract (non-instantiable) base classes for plain-Perl OO",
         "dir" : "/home/runner/work/Class-Abstract/Class-Abstract",
         "finish" : 1781180987.95978,
         "name" : "Class-Abstract",
         "perl" : "5.40.4",
         "run" : "t/extended_tests.t",
         "start" : 1781180987.92224,
         "version" : "0.01"
      },
      {
         "OS" : "linux",
         "abstract" : "Enforce abstract (non-instantiable) base classes for plain-Perl OO",
         "dir" : "/home/runner/work/Class-Abstract/Class-Abstract",
         "finish" : 1781180988.37539,
         "name" : "Class-Abstract",
         "perl" : "5.40.4",
         "run" : "t/function.t",
         "start" : 1781180988.31618,
         "version" : "0.01"
      },
      {
         "OS" : "linux",
         "abstract" : "Enforce abstract (non-instantiable) base classes for plain-Perl OO",
         "dir" : "/home/runner/work/Class-Abstract/Class-Abstract",
         "finish" : 1781180988.80821,
         "name" : "Class-Abstract",
         "perl" : "5.40.4",
         "run" : "t/integration.t",
         "start" : 1781180988.75632,
         "version" : "0.01"
      },
      {
         "OS" : "linux",
         "abstract" : "Enforce abstract (non-instantiable) base classes for plain-Perl OO",
         "dir" : "/home/runner/work/Class-Abstract/Class-Abstract",
         "finish" : 1781180989.18739,
         "name" : "Class-Abstract",
         "perl" : "5.40.4",
         "run" : "t/is_abstract.t",
         "start" : 1781180989.17763,
         "version" : "0.01"
      },
      {
         "OS" : "linux",
         "abstract" : "Enforce abstract (non-instantiable) base classes for plain-Perl OO",
         "dir" : "/home/runner/work/Class-Abstract/Class-Abstract",
         "finish" : 1781180989.53603,
         "name" : "Class-Abstract",
         "perl" : "5.40.4",
         "run" : "t/mutant_killers.t",
         "start" : 1781180989.50847,
         "version" : "0.01"
      },
      {
         "OS" : "linux",
         "abstract" : "Enforce abstract (non-instantiable) base classes for plain-Perl OO",
         "dir" : "/home/runner/work/Class-Abstract/Class-Abstract",
         "finish" : 1781180989.88542,
         "name" : "Class-Abstract",
         "perl" : "5.40.4",
         "run" : "t/override_new.t",
         "start" : 1781180989.87245,
         "version" : "0.01"
      },
      {
         "OS" : "linux",
         "abstract" : "Enforce abstract (non-instantiable) base classes for plain-Perl OO",
         "dir" : "/home/runner/work/Class-Abstract/Class-Abstract",
         "finish" : 1781180990.27788,
         "name" : "Class-Abstract",
         "perl" : "5.40.4",
         "run" : "t/unit.t",
         "start" : 1781180990.2097,
         "version" : "0.01"
      }
   ],
   "summary" : {
      "Total" : {
         "branch" : {
            "covered" : 36,
            "error" : 0,
            "percentage" : 100,
            "total" : 36,
            "uncoverable" : 0
         },
         "condition" : {
            "covered" : 27,
            "error" : 0,
            "percentage" : 100,
            "total" : 27,
            "uncoverable" : 0
         },
         "statement" : {
            "covered" : 60,
            "percentage" : 100,
            "total" : 60
         },
         "subroutine" : {
            "covered" : 14,
            "percentage" : 100,
            "total" : 14
         },
         "total" : {
            "covered" : 137,
            "error" : 0,
            "percentage" : 100,
            "total" : 137,
            "uncoverable" : 0
         }
      },
      "lib/Class/Abstract.pm" : {
         "branch" : {
            "covered" : 36,
            "error" : 0,
            "percentage" : 100,
            "total" : 36,
            "uncoverable" : 0
         },
         "condition" : {
            "covered" : 27,
            "error" : 0,
            "percentage" : 100,
            "total" : 27,
            "uncoverable" : 0
         },
         "statement" : {
            "covered" : 60,
            "percentage" : 100,
            "total" : 60
         },
         "subroutine" : {
            "covered" : 14,
            "percentage" : 100,
            "total" : 14
         },
         "total" : {
            "covered" : 137,
            "error" : 0,
            "percentage" : 100,
            "total" : 137,
            "uncoverable" : 0
         }
      }
   }
}
